HorusAPI/__init__.cpython-39-darwin.so
HorusAPI/extensions.cpython-39-darwin.so
HorusAPI/molstar.cpython-39-darwin.so
HorusAPI/plugins.cpython-39-darwin.so
HorusAPI/smiles.cpython-39-darwin.so
HorusAPI/utils.cpython-39-darwin.so
horusapi-0.8.2.dist-info/METADATA
horusapi-0.8.2.dist-info/WHEEL
horusapi-0.8.2.dist-info/entry_points.txt
horusapi-0.8.2.dist-info/top_level.txt
horusapi-0.8.2.dist-info/RECORD
