Metadata-Version: 2.4
Name: HorusAPI
Version: 0.8.2
Summary: Horus API package for building plugins. Version: 0.8.2
Author: Barcelona Supercomputing Center
Author-email: christian.dominguez@bsc.es
License: ## Horus - MIT
Classifier: Programming Language :: Python
Classifier: Operating System :: OS Independent
Requires-Python: >=3.6
Requires-Dist: pydantic<3,>=2
Requires-Dist: pathvalidate
Dynamic: author
Dynamic: author-email
Dynamic: classifier
Dynamic: description
Dynamic: description-content-type
Dynamic: license
Dynamic: requires-dist
Dynamic: requires-python
Dynamic: summary
